examples/__init__.py
examples/simple_simulation.py
examples/modelling/__init__.py
examples/modelling/functions.py
examples/modelling/mongo.py
examples/modelling/runner.py
examples/modelling/fast_ssc/2048.py
examples/modelling/fast_ssc/4096.py
examples/modelling/fast_ssc/8192_4096.py
examples/modelling/fast_ssc/__init__.py
examples/modelling/fast_ssc/base.py
examples/modelling/rc_scan/8192_4096.py
examples/modelling/rc_scan/__init__.py
examples/modelling/rc_scan/base.py
python_polar_coding/__init__.py
python_polar_coding/channels/__init__.py
python_polar_coding/channels/simple.py
python_polar_coding/modems/__init__.py
python_polar_coding/modems/simple.py
python_polar_coding/polar_codes/__init__.py
python_polar_coding/polar_codes/crc.py
python_polar_coding/polar_codes/pcc.py
python_polar_coding/polar_codes/utils.py
python_polar_coding/polar_codes/base/__init__.py
python_polar_coding/polar_codes/base/codec.py
python_polar_coding/polar_codes/base/constants.py
python_polar_coding/polar_codes/base/decoder.py
python_polar_coding/polar_codes/base/decoding_path.py
python_polar_coding/polar_codes/base/encoder.py
python_polar_coding/polar_codes/base/node.py
python_polar_coding/polar_codes/base/functions/__init__.py
python_polar_coding/polar_codes/base/functions/alpha.py
python_polar_coding/polar_codes/base/functions/beta_hard.py
python_polar_coding/polar_codes/base/functions/beta_soft.py
python_polar_coding/polar_codes/base/functions/encoding.py
python_polar_coding/polar_codes/base/functions/node_types.py
python_polar_coding/polar_codes/fast_scan/__init__.py
python_polar_coding/polar_codes/fast_scan/codec.py
python_polar_coding/polar_codes/fast_scan/decoder.py
python_polar_coding/polar_codes/fast_scan/functions.py
python_polar_coding/polar_codes/fast_scan/node.py
python_polar_coding/polar_codes/fast_ssc/__init__.py
python_polar_coding/polar_codes/fast_ssc/codec.py
python_polar_coding/polar_codes/fast_ssc/decoder.py
python_polar_coding/polar_codes/fast_ssc/node.py
python_polar_coding-0.0.1.dist-info/LICENSE.txt
python_polar_coding-0.0.1.dist-info/METADATA
python_polar_coding-0.0.1.dist-info/WHEEL
python_polar_coding-0.0.1.dist-info/top_level.txt
python_polar_coding-0.0.1.dist-info/RECORD
