Metadata-Version: 2.1
Name: python-polar-coding
Version: 0.0.1
Summary: Polar coding implementation in Python
Home-page: https://github.com/fr0mhell/python-polar-coding
Author: Grigory Timofeev
Author-email: t1m0feev.grigorij@gmail.com
License: UNKNOWN
Project-URL: Bug Report, https://github.com/fr0mhell/python-polar-coding/issues
Project-URL: Source, https://github.com/fr0mhell/python-polar-coding
Keywords: polar codes,fec,simulation
Platform: UNKNOWN
Classifier: Development Status :: 3 - Alpha
Classifier: License :: OSI Approved :: MIT License
Classifier: Programming Language :: Python :: 3
Classifier: Programming Language :: Python :: 3.6
Classifier: Programming Language :: Python :: 3.7
Classifier: Programming Language :: Python :: 3.8
Classifier: Programming Language :: Python :: 3 :: Only
Requires-Python: >=3.6, <4
Requires-Dist: anytree (==2.8.0)
Requires-Dist: certifi (==2020.6.20)
Requires-Dist: chardet (==3.0.4)
Requires-Dist: idna (==2.10)
Requires-Dist: llvmlite (==0.33.0)
Requires-Dist: numba (==0.50.1)
Requires-Dist: numpy (==1.19.1)
Requires-Dist: requests (==2.24.0)
Requires-Dist: six (==1.15.0)
Requires-Dist: urllib3 (==1.25.10)
